MANIFEST.in
README.md
setup.py
version.py
bdgenomics/__init__.py
bdgenomics.adam.egg-info/PKG-INFO
bdgenomics.adam.egg-info/SOURCES.txt
bdgenomics.adam.egg-info/dependency_links.txt
bdgenomics.adam.egg-info/requires.txt
bdgenomics.adam.egg-info/top_level.txt
bdgenomics/adam/__init__.py
bdgenomics/adam/adamContext.py
bdgenomics/adam/ds.py
bdgenomics/adam/find_adam_home.py
bdgenomics/adam/models.py
bdgenomics/adam/stringency.py
bdgenomics/adam/test/__init__.py
bdgenomics/adam/test/adamContext_test.py
bdgenomics/adam/test/alignmentDataset_test.py
bdgenomics/adam/test/coverageDataset_test.py
bdgenomics/adam/test/featureDataset_test.py
bdgenomics/adam/test/genotypeDataset_test.py
bdgenomics/adam/test/variantDataset_test.py
deps/bin/adam-shell
deps/bin/adam-submit
deps/bin/adamR
deps/bin/find-adam-assembly.sh
deps/bin/find-adam-egg.sh
deps/bin/find-adam-home
deps/bin/find-spark.sh
deps/bin/pyadam
deps/jars/adam.jar